Metadata-Version: 2.1
Name: odoo13-addon-hr-timesheet-task-stage
Version: 13.0.1.1.1.dev12
Summary: Open/Close task from corresponding Task Log entry
Home-page: https://github.com/OCA/timesheet
Author: Tecnativa, CorporateHub, Odoo Community Association (OCA)
Author-email: support@odoo-community.org
License: AGPL-3
Platform: UNKNOWN
Classifier: Programming Language :: Python
Classifier: Framework :: Odoo
Classifier: Framework :: Odoo :: 13.0
Classifier: License :: OSI Approved :: GNU Affero General Public License v3
Requires-Python: >=3.5
Requires-Dist: odoo13-addon-project-stage-closed
Requires-Dist: odoo <13.1dev,>=13.0a
